pidmonitor/__init__.py
pidmonitor/bias_detection.cp310-win_amd64.pyd
pidmonitor/data_validation.cp310-win_amd64.pyd
pidmonitor/dbclass.cp310-win_amd64.pyd
pidmonitor/diagnosis_task.cp310-win_amd64.pyd
pidmonitor/mode_estimation.cp310-win_amd64.pyd
pidmonitor/mode_setting.py
pidmonitor/nonlinear_detection.cp310-win_amd64.pyd
pidmonitor/oscillation_detection6.cp310-win_amd64.pyd
pidmonitor/other_tasks.cp310-win_amd64.pyd
pidmonitor/pid_estimate.cp310-win_amd64.pyd
pidmonitor/pidmonitor_task_distribution.cp310-win_amd64.pyd
pidmonitor/saturation_detection.cp310-win_amd64.pyd
pidmonitor/strong_integral_detection.cp310-win_amd64.pyd
pidmonitor/task_response.py
pidmonitor/test_results_analysis3.cp310-win_amd64.pyd
pidmonitor/three_sigma_performance.cp310-win_amd64.pyd
pidmonitor/tsdata_np.cp310-win_amd64.pyd
pidmonitor/utilities.cp310-win_amd64.pyd
taiji_pidmonitor-2.14.0.dist-info/METADATA
taiji_pidmonitor-2.14.0.dist-info/WHEEL
taiji_pidmonitor-2.14.0.dist-info/top_level.txt
taiji_pidmonitor-2.14.0.dist-info/RECORD
