Metadata-Version: 2.4
Name: taiji-pidmonitor
Version: 2.14.0
Summary: Tai-Ji PID monitor algorithm
Author-email: kkzhang <kkzhang3@hotmail.com>
Requires-Python: >=3.10
Requires-Dist: cython
Requires-Dist: numpy
Requires-Dist: scipy
Requires-Dist: taiji_hasp>=0.3.2
Requires-Dist: matplotlib
Requires-Dist: pycryptodome
Requires-Dist: tjcommon
Requires-Dist: tsdbpy
